AuthSys/AuthSys.py
AuthSys/__init__.py
AuthSys-2.0.dist-info/LICENSE
AuthSys-2.0.dist-info/METADATA
AuthSys-2.0.dist-info/WHEEL
AuthSys-2.0.dist-info/top_level.txt
AuthSys-2.0.dist-info/RECORD
